jwst_footprints/__init__.py
jwst_footprints/astro_funcx.py
jwst_footprints/defaults.py
jwst_footprints/ephemeris_old2x.py
jwst_footprints/find_tgt_info.py
jwst_footprints/footprints.py
jwst_footprints/math_extensionsx.py
jwst_footprints/plot_timeline.py
jwst_footprints/quaternionx.py
jwst_footprints/rotationsx.py
jwst_footprints/data/back-08.png
jwst_footprints/data/background.png
jwst_footprints/data/horizons_EM_L2_wrt_Sun_2018_2022.txt
jwst_footprints/data/table-nircam-long.txt
jwst_footprints/data/table-nircam-short.txt
jwst_footprints/data/table-nirspec-ifu.txt
jwst_footprints/data/table-nirspec-msa.txt
jwst_footprints/gui/__init__.py
jwst_footprints/gui/footprints.py
jwst_footprints-2.4.2.dist-info/LICENSE
jwst_footprints-2.4.2.dist-info/METADATA
jwst_footprints-2.4.2.dist-info/WHEEL
jwst_footprints-2.4.2.dist-info/entry_points.txt
jwst_footprints-2.4.2.dist-info/top_level.txt
jwst_footprints-2.4.2.dist-info/RECORD
